DaqC-0.1.12.dist-info/DESCRIPTION.rst
DaqC-0.1.12.dist-info/METADATA
DaqC-0.1.12.dist-info/RECORD
DaqC-0.1.12.dist-info/WHEEL
DaqC-0.1.12.dist-info/entry_points.txt
DaqC-0.1.12.dist-info/metadata.json
DaqC-0.1.12.dist-info/top_level.txt
daqc/__init__.py
daqc/__main__.py
daqc/drasi.py
daqc/file_taker.py
daqc/go4.py
daqc/mbs.py
daqc/mesytec.py
daqc/relay.py
daqc/rest.py
daqc/rundb.py
daqc/secret.py
daqc/settings.py
daqc/state.py
daqc/sync.py
daqc/test_gui.py
daqc/traffic.py
daqc/trigger.py
daqc/ucesb.py
daqc/user.py
daqc/util.py
daqc/vme.py
daqc/watcher.py
daqc/frontend/LICENSE.md
daqc/frontend/bower.json
daqc/frontend/compilerconfig.json
daqc/frontend/compilerconfig.json.defaults
daqc/frontend/index.html
daqc/frontend/package.json
daqc/frontend/css/materialize.css
daqc/frontend/css/style.css
daqc/frontend/images/plugins/bootstrap/css/bootstrap-theme.css
daqc/frontend/images/plugins/bootstrap/css/bootstrap-theme.min.css
daqc/frontend/images/plugins/bootstrap/css/bootstrap.css
daqc/frontend/images/plugins/bootstrap/css/bootstrap.min.css
daqc/frontend/images/plugins/bootstrap/fonts/glyphicons-halflings-regular.eot
daqc/frontend/images/plugins/bootstrap/fonts/glyphicons-halflings-regular.svg
daqc/frontend/images/plugins/bootstrap/fonts/glyphicons-halflings-regular.ttf
daqc/frontend/images/plugins/bootstrap/fonts/glyphicons-halflings-regular.woff
daqc/frontend/images/plugins/bootstrap/fonts/glyphicons-halflings-regular.woff2
daqc/frontend/images/plugins/bootstrap/js/bootstrap.js
daqc/frontend/images/plugins/bootstrap/js/bootstrap.min.js
daqc/frontend/images/plugins/bootstrap/js/npm.js
daqc/frontend/images/plugins/bootstrap-colorpicker/css/bootstrap-colorpicker.css
daqc/frontend/images/plugins/bootstrap-colorpicker/css/bootstrap-colorpicker.css.map
daqc/frontend/images/plugins/bootstrap-colorpicker/css/bootstrap-colorpicker.min.css
daqc/frontend/images/plugins/bootstrap-colorpicker/css/bootstrap-colorpicker.min.css.map
daqc/frontend/images/plugins/bootstrap-colorpicker/img/bootstrap-colorpicker/alpha-horizontal.png
daqc/frontend/images/plugins/bootstrap-colorpicker/img/bootstrap-colorpicker/alpha.png
