Metadata-Version: 2.0
Name: DaqC
Version: 0.1.12
Summary: Controller for the DAQ chain at Arhus University
Home-page: https://git.kern.phys.au.dk/ausa/DAQC
Author: Michael Munch & Jesper Halkjær
Author-email: mm@phys.au.dk
License: MIT
Platform: UNKNOWN
Requires-Dist: cffi
Requires-Dist: flask (>=0.12.1)
Requires-Dist: flask-compress (>=1.4.0)
Requires-Dist: flask-login (>=0.4.0)
Requires-Dist: ptyprocess (>=0.5.1)
Requires-Dist: python-bcrypt (>=0.3.2)
Requires-Dist: pytz
Requires-Dist: pyyaml (>=3.12)
Requires-Dist: requests (>=2.0)
Requires-Dist: watchdog (>=0.8.3)
